odoo10_addon_event_registration_mass_mailing-10.0.1.0.1-py2.7-nspkg.pth
odoo/addons/event_registration_mass_mailing/README.rst
odoo/addons/event_registration_mass_mailing/__init__.py
odoo/addons/event_registration_mass_mailing/__manifest__.py
odoo/addons/event_registration_mass_mailing/i18n/es.po
odoo/addons/event_registration_mass_mailing/models/__init__.py
odoo/addons/event_registration_mass_mailing/models/event_registration.py
odoo/addons/event_registration_mass_mailing/models/mass_mailing.py
odoo/addons/event_registration_mass_mailing/tests/__init__.py
odoo/addons/event_registration_mass_mailing/tests/test_event_registration_mail_list_wizard.py
odoo/addons/event_registration_mass_mailing/views/event_registration.xml
odoo/addons/event_registration_mass_mailing/wizard/__init__.py
odoo/addons/event_registration_mass_mailing/wizard/event_registration_mail_list_wizard.py
odoo/addons/event_registration_mass_mailing/wizard/event_registration_mail_list_wizard.xml
odoo10_addon_event_registration_mass_mailing-10.0.1.0.1.dist-info/DESCRIPTION.rst
odoo10_addon_event_registration_mass_mailing-10.0.1.0.1.dist-info/METADATA
odoo10_addon_event_registration_mass_mailing-10.0.1.0.1.dist-info/RECORD
odoo10_addon_event_registration_mass_mailing-10.0.1.0.1.dist-info/WHEEL
odoo10_addon_event_registration_mass_mailing-10.0.1.0.1.dist-info/metadata.json
odoo10_addon_event_registration_mass_mailing-10.0.1.0.1.dist-info/namespace_packages.txt
odoo10_addon_event_registration_mass_mailing-10.0.1.0.1.dist-info/top_level.txt
